installer/__init__.py
installer/cleanup.py
installer/client_detector.py
installer/main_installer.py
installer/clients/__init__.py
installer/clients/base_client.py
installer/clients/claude_client.py
installer/clients/cursor_client.py
installer/clients/vscode_client.py
installer/clients/windsurf_client.py
mcp_task_orchestrator/__init__.py
mcp_task_orchestrator/__main__.py
mcp_task_orchestrator/enhanced_handlers.py
mcp_task_orchestrator/persistence.py
mcp_task_orchestrator/persistence_factory.py
mcp_task_orchestrator/server.py
mcp_task_orchestrator/config/__init__.py
mcp_task_orchestrator/db/__init__.py
mcp_task_orchestrator/db/auto_migration.py
mcp_task_orchestrator/db/backup_manager.py
mcp_task_orchestrator/db/file_tracking_migration.py
mcp_task_orchestrator/db/generic_repository.py
mcp_task_orchestrator/db/generic_task_migration.py
mcp_task_orchestrator/db/migration.py
mcp_task_orchestrator/db/migration_history.py
mcp_task_orchestrator/db/migration_manager.py
mcp_task_orchestrator/db/models.py
mcp_task_orchestrator/db/persistence.py
mcp_task_orchestrator/db/rollback_manager.py
mcp_task_orchestrator/db/schema_comparator.py
mcp_task_orchestrator/db/workspace_migration.py
mcp_task_orchestrator/db/repository/__init__.py
mcp_task_orchestrator/db/repository/base.py
mcp_task_orchestrator/db/repository/converters.py
mcp_task_orchestrator/db/repository/crud_operations.py
mcp_task_orchestrator/db/repository/dependency_manager.py
mcp_task_orchestrator/db/repository/helpers.py
mcp_task_orchestrator/db/repository/query_builder.py
mcp_task_orchestrator/db/repository/template_operations.py
mcp_task_orchestrator/monitoring/__init__.py
mcp_task_orchestrator/monitoring/hang_detection.py
mcp_task_orchestrator/orchestrator/__init__.py
mcp_task_orchestrator/orchestrator/artifacts.py
mcp_task_orchestrator/orchestrator/context_continuity.py
mcp_task_orchestrator/orchestrator/core.py
mcp_task_orchestrator/orchestrator/decision_tracking.py
mseep_mcp_task_orchestrator-1.8.0.dist-info/licenses/LICENSE
mseep_mcp_task_orchestrator-1.8.0.dist-info/METADATA
mseep_mcp_task_orchestrator-1.8.0.dist-info/WHEEL
mseep_mcp_task_orchestrator-1.8.0.dist-info/top_level.txt
mseep_mcp_task_orchestrator-1.8.0.dist-info/RECORD
