Metadata-Version: 2.4
Name: mseep-mcp-task-orchestrator
Version: 1.8.0
Summary: A Model Context Protocol server for task orchestration
Home-page: https://github.com/EchoingVesper/mcp-task-orchestrator
Author: mseep
Author-email: support@skydeck.ai
Maintainer: mseep
Maintainer-email: support@skydeck.ai
Keywords: mseep,mcp,ai,task-orchestration,claude,automation,llm,workflow
Classifier: Programming Language :: Python :: 3
Classifier: License :: OSI Approved :: MIT License
Classifier: Operating System :: OS Independent
Requires-Python: >=3.6
License-File: LICENSE
Requires-Dist: mcp>=1.9.0
Requires-Dist: pydantic>=2.0.0
Requires-Dist: jinja2>=3.1.0
Requires-Dist: pyyaml>=6.0.0
Requires-Dist: aiofiles>=23.0.0
Requires-Dist: psutil>=5.9.0
Requires-Dist: filelock>=3.12.0
Requires-Dist: sqlalchemy>=2.0.0
Requires-Dist: alembic>=1.10.0
Requires-Dist: typer>=0.9.0
Requires-Dist: rich>=13.0.0
Dynamic: author
Dynamic: author-email
Dynamic: classifier
Dynamic: description
Dynamic: description-content-type
Dynamic: home-page
Dynamic: keywords
Dynamic: license-file
Dynamic: maintainer
Dynamic: maintainer-email
Dynamic: requires-dist
Dynamic: requires-python
Dynamic: summary
